sdarotdl.py
sdarotdl-2.3.1.dist-info/DESCRIPTION.rst
sdarotdl-2.3.1.dist-info/METADATA
sdarotdl-2.3.1.dist-info/RECORD
sdarotdl-2.3.1.dist-info/WHEEL
sdarotdl-2.3.1.dist-info/entry_points.txt
sdarotdl-2.3.1.dist-info/metadata.json
sdarotdl-2.3.1.dist-info/top_level.txt
