Metadata-Version: 2.0
Name: sdarotdl
Version: 2.3.1
Summary: Download videos from sdarot.pm website
Home-page: UNKNOWN
Author: UNKNOWN
Author-email: UNKNOWN
License: UNKNOWN
Platform: UNKNOWN
Requires-Dist: requests (>=2.9.1)
